README.md
hue_sensors_phue.py
setup.py
hue_sensors_phue.egg-info/PKG-INFO
hue_sensors_phue.egg-info/SOURCES.txt
hue_sensors_phue.egg-info/dependency_links.txt
hue_sensors_phue.egg-info/requires.txt
hue_sensors_phue.egg-info/top_level.txt