Metadata-Version: 1.1
Name: hue-sensors-phue
Version: 1.0
Summary: Tools for reading the state of Philips Hue sensors
Home-page: https://github.com/robmarkcole/Hue-sensors-phue
Author: Robin Cole
Author-email: robmarkcole@gmail.com
License: MIT
Keywords: phillips hue
Platform: UNKNOWN
Classifier: Development Status :: 4 - Beta
Classifier: Intended Audience :: Developers
Classifier: License :: OSI Approved :: MIT License
Classifier: Natural Language :: English
Classifier: Programming Language :: Python
Classifier: Programming Language :: Python :: 3
